{"chunk_definitions":[{"row":22,"row_count":1,"visible":true,"expansion_state":0,"options":{"engine":"r","output":false,"label":"unnamed-chunk-176"},"document_id":"47732AE4","chunk_id":"cmyd7i2w249f6","chunk_label":"unnamed-chunk-1"},{"row":39,"row_count":1,"visible":true,"expansion_state":0,"options":{"engine":"r","output":false,"label":"unnamed-chunk-177"},"document_id":"47732AE4","chunk_id":"c3w2ficrqbyme","chunk_label":"unnamed-chunk-2"},{"row":44,"row_count":1,"visible":true,"expansion_state":0,"options":{"engine":"r","output":false,"label":"unnamed-chunk-178"},"document_id":"47732AE4","chunk_id":"cbvdf1jv1c1ll","chunk_label":"unnamed-chunk-3"},{"row":58,"row_count":1,"visible":true,"expansion_state":0,"options":{"engine":"r","output":false,"label":"unnamed-chunk-179"},"document_id":"47732AE4","chunk_id":"ccxmoc985faob","chunk_label":"unnamed-chunk-4"},{"row":76,"row_count":1,"visible":true,"expansion_state":0,"options":{"engine":"r","output":false,"label":"unnamed-chunk-180"},"document_id":"47732AE4","chunk_id":"ch9ld7zt7qq0s","chunk_label":"unnamed-chunk-5"},{"row":92,"row_count":1,"visible":true,"expansion_state":0,"options":{"engine":"r","output":false,"label":"unnamed-chunk-181"},"document_id":"47732AE4","chunk_id":"cw98j5o94zmub","chunk_label":"unnamed-chunk-6"},{"row":98,"row_count":1,"visible":true,"expansion_state":0,"options":{"engine":"r","output":false,"label":"unnamed-chunk-182"},"document_id":"47732AE4","chunk_id":"cxd7r4fg9lhbv","chunk_label":"unnamed-chunk-7"},{"row":113,"row_count":1,"visible":true,"expansion_state":0,"options":{"engine":"r","output":false,"label":"unnamed-chunk-183"},"document_id":"47732AE4","chunk_id":"cqikbxyfsmxgt","chunk_label":"unnamed-chunk-8"},{"row":125,"row_count":1,"visible":true,"expansion_state":0,"options":{"engine":"r","output":false,"label":"unnamed-chunk-184"},"document_id":"47732AE4","chunk_id":"caan6ppsthpwu","chunk_label":"unnamed-chunk-9"},{"row":138,"row_count":1,"visible":true,"expansion_state":0,"options":{"engine":"r","label":"unnamed-chunk-185"},"document_id":"47732AE4","chunk_id":"c9mte852zmjqs","chunk_label":"unnamed-chunk-10"},{"row":159,"row_count":1,"visible":true,"expansion_state":0,"options":{"engine":"r","output":false,"label":"unnamed-chunk-186"},"document_id":"47732AE4","chunk_id":"cgz26tu3ilu5v","chunk_label":"unnamed-chunk-11"},{"row":174,"row_count":1,"visible":true,"expansion_state":0,"options":{"engine":"r","label":"unnamed-chunk-187"},"document_id":"47732AE4","chunk_id":"c34xm2r1i2xi0","chunk_label":"unnamed-chunk-12"},{"row":192,"row_count":1,"visible":true,"expansion_state":0,"options":{"engine":"r","output":false,"label":"unnamed-chunk-188"},"document_id":"47732AE4","chunk_id":"c8lgdloiule66","chunk_label":"unnamed-chunk-13"},{"row":207,"row_count":1,"visible":true,"expansion_state":0,"options":{"engine":"r","label":"unnamed-chunk-189"},"document_id":"47732AE4","chunk_id":"cipukcihl7mj6","chunk_label":"unnamed-chunk-14"},{"row":239,"row_count":1,"visible":true,"expansion_state":0,"options":{"engine":"r","label":"unnamed-chunk-190"},"document_id":"47732AE4","chunk_id":"coizuylanhsab","chunk_label":"unnamed-chunk-15"},{"row":252,"row_count":1,"visible":true,"expansion_state":0,"options":{"engine":"r","label":"unnamed-chunk-191"},"document_id":"47732AE4","chunk_id":"cs2ul5jwg02tl","chunk_label":"unnamed-chunk-16"},{"row":274,"row_count":1,"visible":true,"expansion_state":0,"options":{"engine":"r","label":"unnamed-chunk-192"},"document_id":"47732AE4","chunk_id":"cv041nlkmrwg1","chunk_label":"unnamed-chunk-17"},{"row":345,"row_count":1,"visible":true,"expansion_state":0,"options":{"engine":"r","label":"unnamed-chunk-21"},"document_id":"47732AE4","chunk_id":"c7hjgtbhegxeo","chunk_label":"unnamed-chunk-22"}],"doc_write_time":1700601024,"chunk_rendered_width":682}